README.md
setup.py
src/forml/__init__.py
src/py4ml.egg-info/PKG-INFO
src/py4ml.egg-info/SOURCES.txt
src/py4ml.egg-info/dependency_links.txt
src/py4ml.egg-info/not-zip-safe
src/py4ml.egg-info/requires.txt
src/py4ml.egg-info/top_level.txt