Metadata-Version: 2.1
Name: py4ml
Version: 0.1.dev0
Summary: Lifecycle management framework for Data science projects
Home-page: UNKNOWN
Maintainer: Antony Mayi
Maintainer-email: antonymayi@yahoo.com
License: Apache License 2.0
Platform: UNKNOWN
Classifier: Development Status :: 1 - Planning
Classifier: Environment :: Console
Classifier: Intended Audience :: Developers
Classifier: Intended Audience :: Science/Research
Classifier: License :: Other/Proprietary License
Classifier: Programming Language :: Python :: 3
Classifier: Topic :: Scientific/Engineering :: Artificial Intelligence
Classifier: Topic :: System :: Distributed Computing
Requires-Python: >=3.6
Provides-Extra: doc
Provides-Extra: all
Provides-Extra: stdlib
Provides-Extra: dask
Provides-Extra: graphviz
